lark/__init__.py
lark/_base_client.py
lark/_client.py
lark/_compat.py
lark/_constants.py
lark/_exceptions.py
lark/_files.py
lark/_models.py
lark/_qs.py
lark/_resource.py
lark/_response.py
lark/_streaming.py
lark/_types.py
lark/_version.py
lark/py.typed
lark/_utils/__init__.py
lark/_utils/_compat.py
lark/_utils/_datetime_parse.py
lark/_utils/_logs.py
lark/_utils/_proxy.py
lark/_utils/_reflection.py
lark/_utils/_resources_proxy.py
lark/_utils/_streams.py
lark/_utils/_sync.py
lark/_utils/_transform.py
lark/_utils/_typing.py
lark/_utils/_utils.py
lark/lib/.keep
lark/resources/__init__.py
lark/resources/customer_access.py
lark/resources/customer_portal.py
lark/resources/invoices.py
lark/resources/pricing_metrics.py
lark/resources/rate_cards.py
lark/resources/rate_catalogs.py
lark/resources/subjects.py
lark/resources/subscriptions.py
lark/resources/usage_events.py
lark/resources/subscription_timelines/__init__.py
lark/resources/subscription_timelines/items.py
lark/resources/subscription_timelines/subscription_timelines.py
lark/types/__init__.py
lark/types/amount_input_param.py
lark/types/amount_output.py
lark/types/checkout_callback_param.py
lark/types/customer_access_retrieve_billing_state_response.py
lark/types/customer_portal_create_session_params.py
lark/types/customer_portal_create_session_response.py
lark/types/flat_price_input_param.py
lark/types/flat_price_output.py
lark/types/invoice_list_params.py
lark/types/invoice_list_response.py
lark/types/package_price_input_param.py
lark/types/package_price_output.py
lark/types/period.py
lark/types/period_param.py
lark/types/pricing_metric_create_params.py
lark/types/pricing_metric_create_summary_params.py
lark/types/pricing_metric_create_summary_response.py
lark/types/pricing_metric_list_params.py
lark/types/pricing_metric_list_response.py
lark/types/pricing_metric_resource.py
lark/types/rate_card_create_params.py
lark/types/rate_card_list_params.py
lark/types/rate_card_list_response.py
lark/types/rate_card_resource.py
lark_billing-0.9.0.dist-info/METADATA
lark_billing-0.9.0.dist-info/WHEEL
lark_billing-0.9.0.dist-info/licenses/LICENSE
lark_billing-0.9.0.dist-info/RECORD
